{
  "_comment": "Deterministic safety bounds per airframe class. max_step = largest delta the advisor may propose in a single write. abs_min/abs_max = hard caps regardless of advice. type=int marks integer parameters (written via set_param_int). COMMON entries are merged into every class. Never edited at runtime.",
  "COMMON": {
    "IMU_GYRO_CUTOFF":  { "max_step": 10.0, "abs_min": 8.0, "abs_max": 120.0 },
    "IMU_DGYRO_CUTOFF": { "max_step": 10.0, "abs_min": 8.0, "abs_max": 60.0 },
    "IMU_ACCEL_CUTOFF": { "max_step": 10.0, "abs_min": 8.0, "abs_max": 120.0 },
    "IMU_GYRO_NF0_FRQ": { "max_step": 30.0, "abs_min": 0.0, "abs_max": 419.0 },
    "IMU_GYRO_NF0_BW":  { "max_step": 10.0, "abs_min": 5.0, "abs_max": 100.0 },
    "IMU_GYRO_NF1_FRQ": { "max_step": 30.0, "abs_min": 0.0, "abs_max": 419.0 },
    "IMU_GYRO_NF1_BW":  { "max_step": 10.0, "abs_min": 5.0, "abs_max": 100.0 },
    "IMU_GYRO_DNF_EN":  { "max_step": 3, "abs_min": 0, "abs_max": 3, "type": "int" },
    "IMU_GYRO_DNF_HMC": { "max_step": 2, "abs_min": 1, "abs_max": 7, "type": "int" },
    "IMU_GYRO_DNF_MIN": { "max_step": 20.0, "abs_min": 10.0, "abs_max": 200.0 },
    "IMU_GYRO_DNF_BW":  { "max_step": 5.0, "abs_min": 5.0, "abs_max": 40.0 }
  },
  "MULTIROTOR": {
    "MC_ROLLRATE_P":  { "max_step": 0.03, "abs_min": 0.05, "abs_max": 0.5 },
    "MC_ROLLRATE_I":  { "max_step": 0.05, "abs_min": 0.0,  "abs_max": 0.5 },
    "MC_ROLLRATE_D":  { "max_step": 0.001, "abs_min": 0.0, "abs_max": 0.01 },
    "MC_PITCHRATE_P": { "max_step": 0.03, "abs_min": 0.05, "abs_max": 0.6 },
    "MC_PITCHRATE_I": { "max_step": 0.05, "abs_min": 0.0,  "abs_max": 0.5 },
    "MC_PITCHRATE_D": { "max_step": 0.001, "abs_min": 0.0, "abs_max": 0.01 },
    "MC_YAWRATE_P":   { "max_step": 0.05, "abs_min": 0.05, "abs_max": 0.6 },
    "MC_ROLL_P":      { "max_step": 0.5,  "abs_min": 2.0,  "abs_max": 12.0 },
    "MC_PITCH_P":     { "max_step": 0.5,  "abs_min": 2.0,  "abs_max": 12.0 },
    "MC_YAW_P":       { "max_step": 0.3,  "abs_min": 1.0,  "abs_max": 5.0 },
    "MPC_XY_VEL_P_ACC": { "max_step": 0.2, "abs_min": 1.2, "abs_max": 5.0 },
    "MPC_Z_VEL_P_ACC":  { "max_step": 0.5, "abs_min": 2.0, "abs_max": 8.0 },
    "MPC_XY_P":         { "max_step": 0.1, "abs_min": 0.5, "abs_max": 2.0 },
    "MPC_Z_P":          { "max_step": 0.1, "abs_min": 0.3, "abs_max": 1.5 },
    "IMU_GYRO_NF_FREQ": { "max_step": 30.0, "abs_min": 0.0, "abs_max": 419.0 },
    "IMU_GYRO_NF_BW":   { "max_step": 10.0, "abs_min": 5.0, "abs_max": 100.0 },
    "EKF2_GPS_DELAY":   { "max_step": 50.0, "abs_min": 0.0, "abs_max": 300.0 },
    "EKF2_BARO_DELAY":  { "max_step": 20.0, "abs_min": 0.0, "abs_max": 250.0 },
    "EKF2_MAG_NOISE":   { "max_step": 0.02, "abs_min": 0.001, "abs_max": 1.0 },
    "EKF2_ACC_NOISE":   { "max_step": 0.1,  "abs_min": 0.01, "abs_max": 1.0 },
    "EKF2_GYR_NOISE":   { "max_step": 0.005, "abs_min": 0.0001, "abs_max": 0.1 }
  },
  "FIXED_WING": {
    "FW_RR_P":  { "max_step": 0.02, "abs_min": 0.005, "abs_max": 0.5 },
    "FW_RR_I":  { "max_step": 0.02, "abs_min": 0.0,   "abs_max": 0.5 },
    "FW_PR_P":  { "max_step": 0.02, "abs_min": 0.005, "abs_max": 0.6 },
    "FW_PR_I":  { "max_step": 0.02, "abs_min": 0.0,   "abs_max": 0.5 },
    "FW_YR_P":  { "max_step": 0.02, "abs_min": 0.0,   "abs_max": 0.6 },
    "FW_R_TC":  { "max_step": 0.05, "abs_min": 0.2,   "abs_max": 0.8 },
    "FW_P_TC":  { "max_step": 0.05, "abs_min": 0.2,   "abs_max": 0.8 },
    "FW_AIRSPD_TRIM": { "max_step": 1.0, "abs_min": 10.0, "abs_max": 35.0 },
    "FW_AIRSPD_MIN":  { "max_step": 1.0, "abs_min": 7.0,  "abs_max": 25.0 },
    "FW_MAN_R_SC": { "max_step": 0.1, "abs_min": 0.3, "abs_max": 1.0 },
    "FW_MAN_P_SC": { "max_step": 0.1, "abs_min": 0.3, "abs_max": 1.0 },
    "IMU_GYRO_NF_FREQ": { "max_step": 30.0, "abs_min": 0.0, "abs_max": 419.0 },
    "EKF2_GPS_DELAY":   { "max_step": 50.0, "abs_min": 0.0, "abs_max": 300.0 },
    "EKF2_BARO_DELAY":  { "max_step": 20.0, "abs_min": 0.0, "abs_max": 250.0 },
    "EKF2_MAG_NOISE":   { "max_step": 0.02, "abs_min": 0.001, "abs_max": 1.0 },
    "EKF2_ACC_NOISE":   { "max_step": 0.1,  "abs_min": 0.01, "abs_max": 1.0 },
    "EKF2_GYR_NOISE":   { "max_step": 0.005, "abs_min": 0.0001, "abs_max": 0.1 }
  },
  "DELTA_WING": {
    "FW_RR_P":  { "max_step": 0.015, "abs_min": 0.005, "abs_max": 0.4 },
    "FW_RR_I":  { "max_step": 0.015, "abs_min": 0.0,   "abs_max": 0.4 },
    "FW_PR_P":  { "max_step": 0.015, "abs_min": 0.005, "abs_max": 0.5 },
    "FW_PR_I":  { "max_step": 0.015, "abs_min": 0.0,   "abs_max": 0.4 },
    "FW_R_TC":  { "max_step": 0.05,  "abs_min": 0.2,   "abs_max": 0.8 },
    "FW_AIRSPD_TRIM": { "max_step": 1.0, "abs_min": 10.0, "abs_max": 35.0 },
    "FW_AIRSPD_MIN":  { "max_step": 1.0, "abs_min": 7.0,  "abs_max": 25.0 },
    "FW_MAN_R_SC": { "max_step": 0.1, "abs_min": 0.3, "abs_max": 1.0 },
    "FW_MAN_P_SC": { "max_step": 0.1, "abs_min": 0.3, "abs_max": 1.0 },
    "IMU_GYRO_NF_FREQ": { "max_step": 30.0, "abs_min": 0.0, "abs_max": 419.0 },
    "EKF2_GPS_DELAY":   { "max_step": 50.0, "abs_min": 0.0, "abs_max": 300.0 },
    "EKF2_BARO_DELAY":  { "max_step": 20.0, "abs_min": 0.0, "abs_max": 250.0 },
    "EKF2_MAG_NOISE":   { "max_step": 0.02, "abs_min": 0.001, "abs_max": 1.0 }
  },
  "VTOL": {
    "MC_ROLLRATE_P":  { "max_step": 0.02, "abs_min": 0.05, "abs_max": 0.4 },
    "MC_ROLLRATE_I":  { "max_step": 0.04, "abs_min": 0.0,  "abs_max": 0.4 },
    "MC_ROLLRATE_D":  { "max_step": 0.001, "abs_min": 0.0, "abs_max": 0.01 },
    "MC_PITCHRATE_P": { "max_step": 0.02, "abs_min": 0.05, "abs_max": 0.5 },
    "MC_PITCHRATE_I": { "max_step": 0.04, "abs_min": 0.0,  "abs_max": 0.4 },
    "MC_PITCHRATE_D": { "max_step": 0.001, "abs_min": 0.0, "abs_max": 0.01 },
    "MC_YAWRATE_P":   { "max_step": 0.04, "abs_min": 0.05, "abs_max": 0.5 },
    "MC_ROLL_P":      { "max_step": 0.4,  "abs_min": 2.0,  "abs_max": 10.0 },
    "MC_PITCH_P":     { "max_step": 0.4,  "abs_min": 2.0,  "abs_max": 10.0 },
    "MC_YAW_P":       { "max_step": 0.3,  "abs_min": 1.0,  "abs_max": 5.0 },
    "MPC_XY_VEL_P_ACC": { "max_step": 0.2, "abs_min": 1.2, "abs_max": 5.0 },
    "MPC_Z_VEL_P_ACC":  { "max_step": 0.5, "abs_min": 2.0, "abs_max": 8.0 },
    "MPC_XY_P":         { "max_step": 0.1, "abs_min": 0.5, "abs_max": 2.0 },
    "MPC_Z_P":          { "max_step": 0.1, "abs_min": 0.3, "abs_max": 1.5 },
    "FW_R_TC":        { "max_step": 0.05, "abs_min": 0.2, "abs_max": 0.8 },
    "FW_P_TC":        { "max_step": 0.05, "abs_min": 0.2, "abs_max": 0.8 },
    "FW_RR_P":        { "max_step": 0.015, "abs_min": 0.005, "abs_max": 0.4 },
    "FW_PR_P":        { "max_step": 0.015, "abs_min": 0.005, "abs_max": 0.5 },
    "FW_AIRSPD_TRIM": { "max_step": 1.0, "abs_min": 10.0, "abs_max": 35.0 },
    "FW_AIRSPD_MIN":  { "max_step": 1.0, "abs_min": 7.0,  "abs_max": 25.0 },
    "VT_TRANS_TIMEOUT": { "max_step": 3.0, "abs_min": 5.0, "abs_max": 30.0 },
    "VT_ELEV_MC_LOCK":  { "max_step": 1, "abs_min": 0, "abs_max": 1, "type": "int" },
    "VT_ARSP_TRANS":    { "max_step": 1.0, "abs_min": 6.0, "abs_max": 30.0 },
    "VT_ARSP_BLEND":    { "max_step": 1.0, "abs_min": 0.0, "abs_max": 25.0 },
    "IMU_GYRO_NF_FREQ": { "max_step": 30.0, "abs_min": 0.0, "abs_max": 419.0 },
    "EKF2_GPS_DELAY":   { "max_step": 50.0, "abs_min": 0.0, "abs_max": 300.0 },
    "EKF2_BARO_DELAY":  { "max_step": 20.0, "abs_min": 0.0, "abs_max": 250.0 },
    "EKF2_MAG_NOISE":   { "max_step": 0.02, "abs_min": 0.001, "abs_max": 1.0 },
    "EKF2_ACC_NOISE":   { "max_step": 0.1,  "abs_min": 0.01, "abs_max": 1.0 }
  }
}
